excel_filter_paste/__init__.py
excel_filter_paste/__main__.py
excel_filter_paste/base.py
excel_filter_paste/parse.py
excel_filter_paste/paste.py
excel_filter_paste-0.8.0.dist-info/LICENSE
excel_filter_paste-0.8.0.dist-info/METADATA
excel_filter_paste-0.8.0.dist-info/WHEEL
excel_filter_paste-0.8.0.dist-info/entry_points.txt
excel_filter_paste-0.8.0.dist-info/top_level.txt
excel_filter_paste-0.8.0.dist-info/RECORD
