Metadata-Version: 2.1
Name: excel-filter-paste
Version: 0.8.0
Summary: UNKNOWN
Home-page: UNKNOWN
License: UNKNOWN
Platform: UNKNOWN
License-File: LICENSE
Requires-Dist: openpyxl
Requires-Dist: pandas
Requires-Dist: click
